lemmings/__init__.py
lemmings/cli.py
lemmings/cli_farming.py
lemmings/cli_main.py
lemmings/cli_restart.py
lemmings/cli_status.py
lemmings/lemmingslogging.py
lemmings/__pycache__/__init__.cpython-311.pyc
lemmings/__pycache__/__init__.cpython-313.pyc
lemmings/__pycache__/__init__.cpython-38.pyc
lemmings/__pycache__/cli.cpython-311.pyc
lemmings/__pycache__/cli.cpython-313.pyc
lemmings/__pycache__/cli.cpython-38.pyc
lemmings/__pycache__/cli_farming.cpython-311.pyc
lemmings/__pycache__/cli_farming.cpython-313.pyc
lemmings/__pycache__/cli_farming.cpython-38.pyc
lemmings/__pycache__/cli_main.cpython-311.pyc
lemmings/__pycache__/cli_main.cpython-313.pyc
lemmings/__pycache__/cli_main.cpython-38.pyc
lemmings/__pycache__/cli_status.cpython-311.pyc
lemmings/__pycache__/cli_status.cpython-313.pyc
lemmings/__pycache__/cli_status.cpython-38.pyc
lemmings/__pycache__/lemmingslogging.cpython-311.pyc
lemmings/__pycache__/lemmingslogging.cpython-313.pyc
lemmings/__pycache__/lemmingslogging.cpython-38.pyc
lemmings/base/__init__.py
lemmings/base/database.py
lemmings/base/machine.py
lemmings/base/path_tool.py
lemmings/base/user.py
lemmings/base/__pycache__/__init__.cpython-311.pyc
lemmings/base/__pycache__/__init__.cpython-313.pyc
lemmings/base/__pycache__/__init__.cpython-38.pyc
lemmings/base/__pycache__/database.cpython-311.pyc
lemmings/base/__pycache__/database.cpython-313.pyc
lemmings/base/__pycache__/database.cpython-38.pyc
lemmings/base/__pycache__/machine.cpython-311.pyc
lemmings/base/__pycache__/machine.cpython-313.pyc
lemmings/base/__pycache__/machine.cpython-38.pyc
lemmings/base/__pycache__/path_tool.cpython-311.pyc
lemmings/base/__pycache__/path_tool.cpython-313.pyc
lemmings/base/__pycache__/path_tool.cpython-38.pyc
lemmings/base/__pycache__/user.cpython-311.pyc
lemmings/base/__pycache__/user.cpython-313.pyc
lemmings/base/__pycache__/user.cpython-38.pyc
lemmings/chain/__init__.py
lemmings/chain/chain.py
lemmings/chain/farming.py
lemmings/chain/lemmingjob_base.py
lemmings_hpc-0.9.1.dist-info/licenses/LICENSE.txt
lemmings_hpc-0.9.1.dist-info/METADATA
lemmings_hpc-0.9.1.dist-info/WHEEL
lemmings_hpc-0.9.1.dist-info/entry_points.txt
lemmings_hpc-0.9.1.dist-info/top_level.txt
lemmings_hpc-0.9.1.dist-info/RECORD
