Metadata-Version: 2.4
Name: lemmings-hpc
Version: 0.9.1
Summary: Easy creation of  workflows for recursive and farming HPC jobs
Author: Thibault Gioud,  Jimmy-John Hoste, CoopTeam-CERFACS
Author-email: coop@cerfacs.fr
License: Copyright (c) 2021 Cerfacs/COOP Team
Project-URL: Homepage, https://gitlab.com/cerfacs/lemmings
Project-URL: Documentation, https://lemmings.readthedocs.io/en/latest/
Project-URL: Issues, https://gitlab.com/cerfacs/lemmings/-/issues
Keywords: hpc,job chaining,workflows
Classifier: Programming Language :: Python :: 3.7
Classifier: Programming Language :: Python :: 3.8
Classifier: Programming Language :: Python :: 3.9
Classifier: Programming Language :: Python :: 3.10
Classifier: Programming Language :: Python :: 3.11
Classifier: Programming Language :: Python :: 3.12
Classifier: Programming Language :: Python :: 3.13
Requires-Python: >=3.7
License-File: LICENSE.txt
Requires-Dist: click
Requires-Dist: prettytable<3.0,>=2.0.0
Requires-Dist: numpy
Requires-Dist: PyYAML
Requires-Dist: nob
Requires-Dist: lock
Requires-Dist: loguru
Provides-Extra: tests
Requires-Dist: pytest; extra == "tests"
Requires-Dist: pytest-coverage; extra == "tests"
Requires-Dist: pytest-allclose; extra == "tests"
Requires-Dist: pytest-mock; extra == "tests"
Provides-Extra: docs
Requires-Dist: sphinx_rtd_theme; extra == "docs"
Requires-Dist: recommonmark; extra == "docs"
Dynamic: license-file
